README
flask_websocket.py
setup.py
Flask_WebSocket.egg-info/PKG-INFO
Flask_WebSocket.egg-info/SOURCES.txt
Flask_WebSocket.egg-info/dependency_links.txt
Flask_WebSocket.egg-info/not-zip-safe
Flask_WebSocket.egg-info/requires.txt
Flask_WebSocket.egg-info/top_level.txt