Metadata-Version: 1.1
Name: Flask-WebSocket
Version: 0.1
Summary: simple websocket for Flask
Home-page: http://github.com/damonchen/flask-websocket/
Author: Damon Chen
Author-email: netubu@gmail.com
License: BSD
Platform: any
Classifier: Environment :: Web Environment
Classifier: Intended Audience :: Developers
Classifier: License :: OSI Approved :: BSD License
Classifier: Operating System :: OS Independent
Classifier: Programming Language :: Python
Classifier: Topic :: Internet :: WWW/HTTP :: Dynamic Content
Classifier: Topic :: Software Development :: Libraries :: Python Modules
